{
  "id": "4193509",
  "name": "项目图标",
  "font_family": "iconfont",
  "css_prefix_text": "icon-",
  "description": "",
  "glyphs": [
    {
      "icon_id": "11787972",
      "name": "weather-color-sleet",
      "font_class": "weather-color-sleet",
      "unicode": "e6e4",
      "unicode_decimal": 59108
    },
    {
      "icon_id": "11787973",
      "name": "weather-color-blizzard",
      "font_class": "weather-color-blizzard",
      "unicode": "e6e5",
      "unicode_decimal": 59109
    },
    {
      "icon_id": "11787974",
      "name": "weather-color-loatingdust",
      "font_class": "weather-color-loatingdust",
      "unicode": "e6e6",
      "unicode_decimal": 59110
    },
    {
      "icon_id": "11787975",
      "name": "weather-color-rainstorm",
      "font_class": "weather-color-rainstorm",
      "unicode": "e6e7",
      "unicode_decimal": 59111
    },
    {
      "icon_id": "11788170",
      "name": "weather-color-cloudy",
      "font_class": "weather-color-cloudy",
      "unicode": "e6e8",
      "unicode_decimal": 59112
    },
    {
      "icon_id": "11788212",
      "name": "weather-color-fog",
      "font_class": "weather-color-fog",
      "unicode": "e6e9",
      "unicode_decimal": 59113
    },
    {
      "icon_id": "11788213",
      "name": "weather-color-lightsnow",
      "font_class": "weather-color-lightsnow",
      "unicode": "e6ea",
      "unicode_decimal": 59114
    },
    {
      "icon_id": "11788214",
      "name": "weather-color-partly-cloudy",
      "font_class": "weather-color-partly-cloudy",
      "unicode": "e6eb",
      "unicode_decimal": 59115
    },
    {
      "icon_id": "11788215",
      "name": "weather-color-rain",
      "font_class": "weather-color-rain",
      "unicode": "e6ec",
      "unicode_decimal": 59116
    },
    {
      "icon_id": "11788216",
      "name": "weather-color-middlesnow",
      "font_class": "weather-color-middlesnow",
      "unicode": "e6ed",
      "unicode_decimal": 59117
    },
    {
      "icon_id": "11788217",
      "name": "weather-color-partly-cloudy-night",
      "font_class": "weather-color-partly-cloudy-night",
      "unicode": "e6ee",
      "unicode_decimal": 59118
    },
    {
      "icon_id": "11788219",
      "name": "weather-color-sunny",
      "font_class": "weather-color-sunny",
      "unicode": "e6ef",
      "unicode_decimal": 59119
    },
    {
      "icon_id": "11788220",
      "name": "weather-color-sand-dust",
      "font_class": "weather-color-sand-dust",
      "unicode": "e6f0",
      "unicode_decimal": 59120
    },
    {
      "icon_id": "11788221",
      "name": "weather-color-wind-a",
      "font_class": "weather-color-wind-a",
      "unicode": "e6f1",
      "unicode_decimal": 59121
    },
    {
      "icon_id": "11788222",
      "name": "weather-color-wind-b",
      "font_class": "weather-color-wind-b",
      "unicode": "e6f2",
      "unicode_decimal": 59122
    },
    {
      "icon_id": "11788223",
      "name": "weather-color-snow",
      "font_class": "weather-color-snow",
      "unicode": "e6f3",
      "unicode_decimal": 59123
    },
    {
      "icon_id": "11788224",
      "name": "weather-color-sunny-night",
      "font_class": "weather-color-sunny-night",
      "unicode": "e6f4",
      "unicode_decimal": 59124
    },
    {
      "icon_id": "11788225",
      "name": "weather-color-thunder",
      "font_class": "weather-color-thunder",
      "unicode": "e6f5",
      "unicode_decimal": 59125
    },
    {
      "icon_id": "11788226",
      "name": "weather-color-wind",
      "font_class": "weather-color-wind",
      "unicode": "e6f6",
      "unicode_decimal": 59126
    },
    {
      "icon_id": "11788227",
      "name": "weather-color-middlerain",
      "font_class": "weather-color-middlerain",
      "unicode": "e6f7",
      "unicode_decimal": 59127
    },
    {
      "icon_id": "11788228",
      "name": "weather-color-lightrain",
      "font_class": "weather-color-lightrain",
      "unicode": "e6f8",
      "unicode_decimal": 59128
    },
    {
      "icon_id": "11788229",
      "name": "weather-color-smog",
      "font_class": "weather-color-smog",
      "unicode": "e6f9",
      "unicode_decimal": 59129
    },
    {
      "icon_id": "11788256",
      "name": "universal-color-decline",
      "font_class": "universal-decline",
      "unicode": "e6fa",
      "unicode_decimal": 59130
    },
    {
      "icon_id": "11788257",
      "name": "universal-color-rise",
      "font_class": "universal-rise",
      "unicode": "e6fb",
      "unicode_decimal": 59131
    },
    {
      "icon_id": "11788371",
      "name": "universal-document-excel",
      "font_class": "document-excel",
      "unicode": "e6fc",
      "unicode_decimal": 59132
    },
    {
      "icon_id": "11788372",
      "name": "universal-document-word",
      "font_class": "document-word",
      "unicode": "e6fd",
      "unicode_decimal": 59133
    },
    {
      "icon_id": "11788373",
      "name": "universal-document-pdf",
      "font_class": "document-pdf",
      "unicode": "e6fe",
      "unicode_decimal": 59134
    },
    {
      "icon_id": "14376603",
      "name": "weather-color-thundershower",
      "font_class": "weather-color-thundershower",
      "unicode": "e6ff",
      "unicode_decimal": 59135
    },
    {
      "icon_id": "7693781",
      "name": "accumulated-temperat",
      "font_class": "accumulated-temperat",
      "unicode": "e7f7",
      "unicode_decimal": 59383
    },
    {
      "icon_id": "11062483",
      "name": "universal-list",
      "font_class": "universal-list",
      "unicode": "e68d",
      "unicode_decimal": 59021
    },
    {
      "icon_id": "7693782",
      "name": "cloudy-sun",
      "font_class": "cloudy-sun",
      "unicode": "e7f8",
      "unicode_decimal": 59384
    },
    {
      "icon_id": "11115629",
      "name": "universal-light",
      "font_class": "universal-light",
      "unicode": "e68e",
      "unicode_decimal": 59022
    },
    {
      "icon_id": "7693783",
      "name": "cloudy-moon",
      "font_class": "cloudy-moon",
      "unicode": "e7f9",
      "unicode_decimal": 59385
    },
    {
      "icon_id": "11115648",
      "name": "universal-tourist",
      "font_class": "universal-tourist",
      "unicode": "e68f",
      "unicode_decimal": 59023
    },
    {
      "icon_id": "7693784",
      "name": "fly-ash",
      "font_class": "fly-ash",
      "unicode": "e7fa",
      "unicode_decimal": 59386
    },
    {
      "icon_id": "11115649",
      "name": "universal-money",
      "font_class": "universal-money",
      "unicode": "e690",
      "unicode_decimal": 59024
    },
    {
      "icon_id": "7693785",
      "name": "fog-light",
      "font_class": "fog-light",
      "unicode": "e7fb",
      "unicode_decimal": 59387
    },
    {
      "icon_id": "11115665",
      "name": "agriculture-plant",
      "font_class": "agriculture-plant",
      "unicode": "e691",
      "unicode_decimal": 59025
    },
    {
      "icon_id": "7693786",
      "name": "fog-normal",
      "font_class": "fog-normal",
      "unicode": "e7fc",
      "unicode_decimal": 59388
    },
    {
      "icon_id": "11115667",
      "name": "agriculture-seaweed",
      "font_class": "agriculture-seaweed",
      "unicode": "e692",
      "unicode_decimal": 59026
    },
    {
      "icon_id": "7693787",
      "name": "fog-severity",
      "font_class": "fog-severity",
      "unicode": "e7fd",
      "unicode_decimal": 59389
    },
    {
      "icon_id": "11115720",
      "name": "direction-fill-down",
      "font_class": "direction-fill-down",
      "unicode": "e693",
      "unicode_decimal": 59027
    },
    {
      "icon_id": "7693788",
      "name": "cloud",
      "font_class": "cloud",
      "unicode": "e7fe",
      "unicode_decimal": 59390
    },
    {
      "icon_id": "11115721",
      "name": "direction-fill-left",
      "font_class": "direction-fill-left",
      "unicode": "e694",
      "unicode_decimal": 59028
    },
    {
      "icon_id": "7693789",
      "name": "freezing-rain",
      "font_class": "freezing-rain",
      "unicode": "e7ff",
      "unicode_decimal": 59391
    },
    {
      "icon_id": "11115722",
      "name": "direction-fill-up",
      "font_class": "direction-fill-up",
      "unicode": "e695",
      "unicode_decimal": 59029
    },
    {
      "icon_id": "7693790",
      "name": "frost",
      "font_class": "frost",
      "unicode": "e800",
      "unicode_decimal": 59392
    },
    {
      "icon_id": "11115723",
      "name": "direction-fill-right",
      "font_class": "direction-fill-right",
      "unicode": "e696",
      "unicode_decimal": 59030
    },
    {
      "icon_id": "7693791",
      "name": "hailstone",
      "font_class": "hailstone",
      "unicode": "e801",
      "unicode_decimal": 59393
    },
    {
      "icon_id": "11178453",
      "name": "agriculture-pig-b",
      "font_class": "agriculture-pig-b",
      "unicode": "e697",
      "unicode_decimal": 59031
    },
    {
      "icon_id": "7693792",
      "name": "haze",
      "font_class": "haze",
      "unicode": "e802",
      "unicode_decimal": 59394
    },
    {
      "icon_id": "11178454",
      "name": "agriculture-farm",
      "font_class": "agriculture-farm",
      "unicode": "e698",
      "unicode_decimal": 59032
    },
    {
      "icon_id": "7693793",
      "name": "humidity",
      "font_class": "humidity",
      "unicode": "e803",
      "unicode_decimal": 59395
    },
    {
      "icon_id": "11178455",
      "name": "agriculture-ship",
      "font_class": "agriculture-ship",
      "unicode": "e699",
      "unicode_decimal": 59033
    },
    {
      "icon_id": "7693794",
      "name": "lightning",
      "font_class": "lightning",
      "unicode": "e804",
      "unicode_decimal": 59396
    },
    {
      "icon_id": "11178456",
      "name": "agriculture-boat",
      "font_class": "agriculture-boat",
      "unicode": "e69a",
      "unicode_decimal": 59034
    },
    {
      "icon_id": "7693795",
      "name": "high-temperature",
      "font_class": "high-temperature",
      "unicode": "e805",
      "unicode_decimal": 59397
    },
    {
      "icon_id": "11178457",
      "name": "agriculture-rice",
      "font_class": "agriculture-rice",
      "unicode": "e69b",
      "unicode_decimal": 59035
    },
    {
      "icon_id": "7693796",
      "name": "moon",
      "font_class": "moon",
      "unicode": "e806",
      "unicode_decimal": 59398
    },
    {
      "icon_id": "11178458",
      "name": "agriculture-wheat",
      "font_class": "agriculture-wheat",
      "unicode": "e69c",
      "unicode_decimal": 59036
    },
    {
      "icon_id": "7693797",
      "name": "precipitation",
      "font_class": "precipitation",
      "unicode": "e807",
      "unicode_decimal": 59399
    },
    {
      "icon_id": "11178459",
      "name": "agriculture-pig-a",
      "font_class": "agriculture-pig-a",
      "unicode": "e69d",
      "unicode_decimal": 59037
    },
    {
      "icon_id": "7693798",
      "name": "rain-light",
      "font_class": "rain-light",
      "unicode": "e808",
      "unicode_decimal": 59400
    },
    {
      "icon_id": "11178460",
      "name": "agriculture-granary-rice",
      "font_class": "agriculture-granary-rice",
      "unicode": "e69e",
      "unicode_decimal": 59038
    },
    {
      "icon_id": "7693799",
      "name": "rain-moderate",
      "font_class": "rain-moderate",
      "unicode": "e809",
      "unicode_decimal": 59401
    },
    {
      "icon_id": "11178461",
      "name": "agriculture-granary-wheat",
      "font_class": "agriculture-granary-wheat",
      "unicode": "e69f",
      "unicode_decimal": 59039
    },
    {
      "icon_id": "7693800",
      "name": "low-temperature",
      "font_class": "low-temperature",
      "unicode": "e80a",
      "unicode_decimal": 59402
    },
    {
      "icon_id": "11265113",
      "name": "universal-monitor",
      "font_class": "universal-monitor",
      "unicode": "e6a0",
      "unicode_decimal": 59040
    },
    {
      "icon_id": "7693801",
      "name": "rain-heavy",
      "font_class": "rain-heavy",
      "unicode": "e80b",
      "unicode_decimal": 59403
    },
    {
      "icon_id": "11265114",
      "name": "universal-weather-station",
      "font_class": "universal-weather-station",
      "unicode": "e6a1",
      "unicode_decimal": 59041
    },
    {
      "icon_id": "7693802",
      "name": "sand-storm",
      "font_class": "sand-storm",
      "unicode": "e80c",
      "unicode_decimal": 59404
    },
    {
      "icon_id": "11265115",
      "name": "universal-ph",
      "font_class": "universal-ph",
      "unicode": "e6a2",
      "unicode_decimal": 59042
    },
    {
      "icon_id": "7693803",
      "name": "sand-blowing",
      "font_class": "sand-blowing",
      "unicode": "e80d",
      "unicode_decimal": 59405
    },
    {
      "icon_id": "11265128",
      "name": "agriculture-fishery",
      "font_class": "agriculture-fishery",
      "unicode": "e6a3",
      "unicode_decimal": 59043
    },
    {
      "icon_id": "7693804",
      "name": "rain-serious",
      "font_class": "rain-serious",
      "unicode": "e80e",
      "unicode_decimal": 59406
    },
    {
      "icon_id": "11265145",
      "name": "soil-temperature-b",
      "font_class": "soil-temperature-b",
      "unicode": "e6a4",
      "unicode_decimal": 59044
    },
    {
      "icon_id": "7693805",
      "name": "rain-snow",
      "font_class": "rain-snow",
      "unicode": "e80f",
      "unicode_decimal": 59407
    },
    {
      "icon_id": "11265146",
      "name": "disaster-oxygen",
      "font_class": "disaster-oxygen",
      "unicode": "e6a5",
      "unicode_decimal": 59045
    },
    {
      "icon_id": "7693806",
      "name": "shower",
      "font_class": "shower",
      "unicode": "e810",
      "unicode_decimal": 59408
    },
    {
      "icon_id": "11265180",
      "name": "universal-user-c",
      "font_class": "universal-user-c",
      "unicode": "e6a6",
      "unicode_decimal": 59046
    },
    {
      "icon_id": "7693807",
      "name": "snow-light",
      "font_class": "snow-light",
      "unicode": "e811",
      "unicode_decimal": 59409
    },
    {
      "icon_id": "11265788",
      "name": "heavyfog",
      "font_class": "heavyfog",
      "unicode": "e6a8",
      "unicode_decimal": 59048
    },
    {
      "icon_id": "7693808",
      "name": "snow-moderate",
      "font_class": "snow-moderate",
      "unicode": "e812",
      "unicode_decimal": 59410
    },
    {
      "icon_id": "11265791",
      "name": "roadicing",
      "font_class": "roadicing",
      "unicode": "e6ab",
      "unicode_decimal": 59051
    },
    {
      "icon_id": "7693809",
      "name": "sun",
      "font_class": "sun",
      "unicode": "e813",
      "unicode_decimal": 59411
    },
    {
      "icon_id": "11265952",
      "name": "weather-fill-hail",
      "font_class": "hail-a",
      "unicode": "e6a7",
      "unicode_decimal": 59047
    },
    {
      "icon_id": "7693810",
      "name": "snow-heavy",
      "font_class": "snow-heavy",
      "unicode": "e814",
      "unicode_decimal": 59412
    },
    {
      "icon_id": "11265953",
      "name": "weather-fill-drought",
      "font_class": "drought-b",
      "unicode": "e6a9",
      "unicode_decimal": 59049
    },
    {
      "icon_id": "7693811",
      "name": "snow-severity",
      "font_class": "snow-severity",
      "unicode": "e815",
      "unicode_decimal": 59413
    },
    {
      "icon_id": "11265954",
      "name": "weather-fill-frost",
      "font_class": "frost-b",
      "unicode": "e6aa",
      "unicode_decimal": 59050
    },
    {
      "icon_id": "7693812",
      "name": "snow",
      "font_class": "snow",
      "unicode": "e816",
      "unicode_decimal": 59414
    },
    {
      "icon_id": "11265955",
      "name": "weather-fill-haze",
      "font_class": "haze-a",
      "unicode": "e6ac",
      "unicode_decimal": 59052
    },
    {
      "icon_id": "7693813",
      "name": "wind-force5",
      "font_class": "wind-force5",
      "unicode": "e817",
      "unicode_decimal": 59415
    },
    {
      "icon_id": "11265956",
      "name": "weather-fill-sandstorm",
      "font_class": "sandstorm-a",
      "unicode": "e6ad",
      "unicode_decimal": 59053
    },
    {
      "icon_id": "7693814",
      "name": "wind-force6",
      "font_class": "wind-force6",
      "unicode": "e818",
      "unicode_decimal": 59416
    },
    {
      "icon_id": "11265957",
      "name": "weather-fill-blizzard",
      "font_class": "blizzard-a",
      "unicode": "e6ae",
      "unicode_decimal": 59054
    },
    {
      "icon_id": "7693815",
      "name": "wind-force7",
      "font_class": "wind-force7",
      "unicode": "e819",
      "unicode_decimal": 59417
    },
    {
      "icon_id": "11394735",
      "name": "universal-folder-b",
      "font_class": "universal-folder-b",
      "unicode": "e6af",
      "unicode_decimal": 59055
    },
    {
      "icon_id": "7693816",
      "name": "typhoon",
      "font_class": "typhoon",
      "unicode": "e81a",
      "unicode_decimal": 59418
    },
    {
      "icon_id": "11394736",
      "name": "universal-company",
      "font_class": "universal-company",
      "unicode": "e6b0",
      "unicode_decimal": 59056
    },
    {
      "icon_id": "7693817",
      "name": "thundershowe",
      "font_class": "thundershowe",
      "unicode": "e81b",
      "unicode_decimal": 59419
    },
    {
      "icon_id": "11394737",
      "name": "universal-tag",
      "font_class": "universal-tag",
      "unicode": "e6b1",
      "unicode_decimal": 59057
    },
    {
      "icon_id": "7693818",
      "name": "wind-force9",
      "font_class": "wind-force9",
      "unicode": "e81c",
      "unicode_decimal": 59420
    },
    {
      "icon_id": "11442569",
      "name": "universal-transport",
      "font_class": "universal-transport",
      "unicode": "e6c2",
      "unicode_decimal": 59074
    },
    {
      "icon_id": "7693819",
      "name": "wind-force8",
      "font_class": "wind-force8",
      "unicode": "e81d",
      "unicode_decimal": 59421
    },
    {
      "icon_id": "11442571",
      "name": "agriculture-pig-c",
      "font_class": "agriculture-pig-c",
      "unicode": "e6c3",
      "unicode_decimal": 59075
    },
    {
      "icon_id": "7693820",
      "name": "wind-force12",
      "font_class": "wind-force12",
      "unicode": "e81e",
      "unicode_decimal": 59422
    },
    {
      "icon_id": "11770996",
      "name": "universal-order-complaint",
      "font_class": "universal-order-complaint",
      "unicode": "e6c4",
      "unicode_decimal": 59076
    },
    {
      "icon_id": "7693821",
      "name": "wind-force11",
      "font_class": "wind-force11",
      "unicode": "e81f",
      "unicode_decimal": 59423
    },
    {
      "icon_id": "12045210",
      "name": "universal-map-track",
      "font_class": "universal-map-track",
      "unicode": "e6b2",
      "unicode_decimal": 59058
    },
    {
      "icon_id": "7693822",
      "name": "wind-force10",
      "font_class": "wind-force10",
      "unicode": "e820",
      "unicode_decimal": 59424
    },
    {
      "icon_id": "12045211",
      "name": "universal-electric-fence",
      "font_class": "universal-electric-fence",
      "unicode": "e6b3",
      "unicode_decimal": 59059
    },
    {
      "icon_id": "7693823",
      "name": "wind-force4",
      "font_class": "wind-force4",
      "unicode": "e821",
      "unicode_decimal": 59425
    },
    {
      "icon_id": "12045212",
      "name": "universal-progress",
      "font_class": "universal-progress",
      "unicode": "e6b4",
      "unicode_decimal": 59060
    },
    {
      "icon_id": "7693824",
      "name": "wind-grade",
      "font_class": "wind-grade",
      "unicode": "e822",
      "unicode_decimal": 59426
    },
    {
      "icon_id": "12045214",
      "name": "universal-alarm-b",
      "font_class": "universal-alarm-b",
      "unicode": "e6b5",
      "unicode_decimal": 59061
    },
    {
      "icon_id": "7693880",
      "name": "precipitation-1",
      "font_class": "precipitation-1",
      "unicode": "e823",
      "unicode_decimal": 59427
    },
    {
      "icon_id": "12045231",
      "name": "universal-progress",
      "font_class": "universal-progress-copy",
      "unicode": "e889",
      "unicode_decimal": 59529
    },
    {
      "icon_id": "7693881",
      "name": "precipitation-2",
      "font_class": "precipitation-2",
      "unicode": "e824",
      "unicode_decimal": 59428
    },
    {
      "icon_id": "12045238",
      "name": "agriculture-farmland-a",
      "font_class": "agriculture-farmland-a",
      "unicode": "e6b6",
      "unicode_decimal": 59062
    },
    {
      "icon_id": "7693882",
      "name": "precipitation-3",
      "font_class": "precipitation-3",
      "unicode": "e825",
      "unicode_decimal": 59429
    },
    {
      "icon_id": "12045326",
      "name": "universal-order-survey",
      "font_class": "universal-order-survey",
      "unicode": "e6b7",
      "unicode_decimal": 59063
    },
    {
      "icon_id": "7693883",
      "name": "precipitation-4",
      "font_class": "precipitation-4",
      "unicode": "e826",
      "unicode_decimal": 59430
    },
    {
      "icon_id": "12045755",
      "name": "universal-help-a",
      "font_class": "universal-help-a",
      "unicode": "e6b8",
      "unicode_decimal": 59064
    },
    {
      "icon_id": "7693884",
      "name": "precipitation-no",
      "font_class": "precipitation-no",
      "unicode": "e827",
      "unicode_decimal": 59431
    },
    {
      "icon_id": "12448719",
      "name": "agriculture-leaf-c",
      "font_class": "agriculture-leaf-c",
      "unicode": "e6b9",
      "unicode_decimal": 59065
    },
    {
      "icon_id": "7694646",
      "name": "cold-wave",
      "font_class": "cold-wave",
      "unicode": "e828",
      "unicode_decimal": 59432
    },
    {
      "icon_id": "12498414",
      "name": "universal-select",
      "font_class": "universal-select",
      "unicode": "e6ba",
      "unicode_decimal": 59066
    },
    {
      "icon_id": "7694647",
      "name": "gale",
      "font_class": "gale",
      "unicode": "e829",
      "unicode_decimal": 59433
    },
    {
      "icon_id": "13102437",
      "name": "universal-publicityboard",
      "font_class": "universal-publicityboard",
      "unicode": "e6bb",
      "unicode_decimal": 59067
    },
    {
      "icon_id": "7694648",
      "name": "high-temperature",
      "font_class": "high-temperature1",
      "unicode": "e82a",
      "unicode_decimal": 59434
    },
    {
      "icon_id": "13102438",
      "name": "universal-idpoint",
      "font_class": "universal-idpoint",
      "unicode": "e6bc",
      "unicode_decimal": 59068
    },
    {
      "icon_id": "7694649",
      "name": "lightning",
      "font_class": "lightning-a",
      "unicode": "e82b",
      "unicode_decimal": 59435
    },
    {
      "icon_id": "13102439",
      "name": "universal-shopping-cart",
      "font_class": "universal-shopping-cart",
      "unicode": "e6bd",
      "unicode_decimal": 59069
    },
    {
      "icon_id": "7694650",
      "name": "typhoon-filled",
      "font_class": "typhoon-filled",
      "unicode": "e82c",
      "unicode_decimal": 59436
    },
    {
      "icon_id": "13102535",
      "name": "universal-point-triangle",
      "font_class": "universal-point-triangle",
      "unicode": "e6be",
      "unicode_decimal": 59070
    },
    {
      "icon_id": "7694651",
      "name": "rainstorm-filled",
      "font_class": "rainstorm-filled",
      "unicode": "e82d",
      "unicode_decimal": 59437
    },
    {
      "icon_id": "13252043",
      "name": "universal-maplayer",
      "font_class": "universal-maplayer",
      "unicode": "e6bf",
      "unicode_decimal": 59071
    },
    {
      "icon_id": "7697778",
      "name": "location-2",
      "font_class": "location-2",
      "unicode": "e847",
      "unicode_decimal": 59463
    },
    {
      "icon_id": "13331088",
      "name": "universal-chart-point",
      "font_class": "universal-chart-point",
      "unicode": "e6c0",
      "unicode_decimal": 59072
    },
    {
      "icon_id": "7697779",
      "name": "location-3",
      "font_class": "location-3",
      "unicode": "e848",
      "unicode_decimal": 59464
    },
    {
      "icon_id": "13554505",
      "name": "universal-compass",
      "font_class": "universal-compass",
      "unicode": "e6c1",
      "unicode_decimal": 59073
    },
    {
      "icon_id": "7697780",
      "name": "location",
      "font_class": "location",
      "unicode": "e849",
      "unicode_decimal": 59465
    },
    {
      "icon_id": "13580736",
      "name": "universal-file-import-a",
      "font_class": "universal-file-import-a",
      "unicode": "e6c5",
      "unicode_decimal": 59077
    },
    {
      "icon_id": "7742287",
      "name": "tree-2",
      "font_class": "tree-2",
      "unicode": "e84a",
      "unicode_decimal": 59466
    },
    {
      "icon_id": "13580737",
      "name": "universal-map-earth",
      "font_class": "universal-map-earth",
      "unicode": "e6c6",
      "unicode_decimal": 59078
    },
    {
      "icon_id": "7742288",
      "name": "tree-3",
      "font_class": "tree-3",
      "unicode": "e84b",
      "unicode_decimal": 59467
    },
    {
      "icon_id": "13727378",
      "name": "universal-merge",
      "font_class": "universal-merge",
      "unicode": "e6c7",
      "unicode_decimal": 59079
    },
    {
      "icon_id": "7742289",
      "name": "tree-4",
      "font_class": "tree-4",
      "unicode": "e84c",
      "unicode_decimal": 59468
    },
    {
      "icon_id": "13727379",
      "name": "universal-split",
      "font_class": "universal-split",
      "unicode": "e6c8",
      "unicode_decimal": 59080
    },
    {
      "icon_id": "7742290",
      "name": "tree-6",
      "font_class": "tree-6",
      "unicode": "e84d",
      "unicode_decimal": 59469
    },
    {
      "icon_id": "13727380",
      "name": "universal-add-farmland",
      "font_class": "universal-add-farmland",
      "unicode": "e6c9",
      "unicode_decimal": 59081
    },
    {
      "icon_id": "7742291",
      "name": "tree-7",
      "font_class": "tree-7",
      "unicode": "e84e",
      "unicode_decimal": 59470
    },
    {
      "icon_id": "13727750",
      "name": "universal-farmland-add-a",
      "font_class": "universal-farmland-add-a",
      "unicode": "e6ca",
      "unicode_decimal": 59082
    },
    {
      "icon_id": "7742292",
      "name": "tree",
      "font_class": "tree",
      "unicode": "e84f",
      "unicode_decimal": 59471
    },
    {
      "icon_id": "13727787",
      "name": "universal-cancel-a",
      "font_class": "universal-cancel-a",
      "unicode": "e6cb",
      "unicode_decimal": 59083
    },
    {
      "icon_id": "7742293",
      "name": "tree-5",
      "font_class": "tree-5",
      "unicode": "e850",
      "unicode_decimal": 59472
    },
    {
      "icon_id": "13727788",
      "name": "universal-batch-selection",
      "font_class": "universal-batch-selection",
      "unicode": "e6cc",
      "unicode_decimal": 59084
    },
    {
      "icon_id": "7742315",
      "name": "flowerpot-leaf",
      "font_class": "flowerpot-leaf",
      "unicode": "e851",
      "unicode_decimal": 59473
    },
    {
      "icon_id": "13727789",
      "name": "universal-file-document-land",
      "font_class": "universal-file-document-land",
      "unicode": "e6cd",
      "unicode_decimal": 59085
    },
    {
      "icon_id": "7742316",
      "name": "fire",
      "font_class": "fire",
      "unicode": "e852",
      "unicode_decimal": 59474
    },
    {
      "icon_id": "13727818",
      "name": "universal-trash",
      "font_class": "universal-trash",
      "unicode": "e6ce",
      "unicode_decimal": 59086
    },
    {
      "icon_id": "7742317",
      "name": "leaf-2",
      "font_class": "leaf-2",
      "unicode": "e853",
      "unicode_decimal": 59475
    },
    {
      "icon_id": "13727832",
      "name": "direction-fill-mini-down",
      "font_class": "direction-fill-mini-down",
      "unicode": "e6cf",
      "unicode_decimal": 59087
    },
    {
      "icon_id": "7742402",
      "name": "appstore-2",
      "font_class": "appstore-2",
      "unicode": "e854",
      "unicode_decimal": 59476
    },
    {
      "icon_id": "13727833",
      "name": "direction-fill-mini-up",
      "font_class": "direction-fill-mini-up",
      "unicode": "e6d0",
      "unicode_decimal": 59088
    },
    {
      "icon_id": "7742431",
      "name": "swap-2",
      "font_class": "swap-2",
      "unicode": "e855",
      "unicode_decimal": 59477
    },
    {
      "icon_id": "13727834",
      "name": "direction-fill-mini-right",
      "font_class": "direction-fill-mini-right",
      "unicode": "e6d1",
      "unicode_decimal": 59089
    },
    {
      "icon_id": "7742477",
      "name": "list",
      "font_class": "list",
      "unicode": "e856",
      "unicode_decimal": 59478
    },
    {
      "icon_id": "13727835",
      "name": "direction-fill-mini-left",
      "font_class": "direction-fill-mini-left",
      "unicode": "e6d2",
      "unicode_decimal": 59090
    },
    {
      "icon_id": "7742722",
      "name": "atlas",
      "font_class": "atlas",
      "unicode": "e857",
      "unicode_decimal": 59479
    },
    {
      "icon_id": "13896750",
      "name": "universal-file-docsearch",
      "font_class": "universal-file-docsearch",
      "unicode": "e6d3",
      "unicode_decimal": 59091
    },
    {
      "icon_id": "7742723",
      "name": "ecology",
      "font_class": "ecology",
      "unicode": "e858",
      "unicode_decimal": 59480
    },
    {
      "icon_id": "13896751",
      "name": "agriculture-garden",
      "font_class": "agriculture-garden",
      "unicode": "e6d4",
      "unicode_decimal": 59092
    },
    {
      "icon_id": "7742724",
      "name": "science",
      "font_class": "science",
      "unicode": "e859",
      "unicode_decimal": 59481
    },
    {
      "icon_id": "13896752",
      "name": "chart-statistics",
      "font_class": "chart-statistics",
      "unicode": "e6d5",
      "unicode_decimal": 59093
    },
    {
      "icon_id": "7742798",
      "name": "flask",
      "font_class": "flask",
      "unicode": "e85a",
      "unicode_decimal": 59482
    },
    {
      "icon_id": "13896753",
      "name": "universal-map-ruler-s",
      "font_class": "universal-map-ruler-s",
      "unicode": "e6d6",
      "unicode_decimal": 59094
    },
    {
      "icon_id": "7744470",
      "name": "animal-cattle",
      "font_class": "animal-cattle",
      "unicode": "e85b",
      "unicode_decimal": 59483
    },
    {
      "icon_id": "13896754",
      "name": "universal-map-ruler",
      "font_class": "universal-map-ruler",
      "unicode": "e6d7",
      "unicode_decimal": 59095
    },
    {
      "icon_id": "7744471",
      "name": "animal-chicken",
      "font_class": "animal-chicken",
      "unicode": "e85c",
      "unicode_decimal": 59484
    },
    {
      "icon_id": "13896755",
      "name": "agriculture-grapefruit",
      "font_class": "agriculture-grapefruit",
      "unicode": "e6d8",
      "unicode_decimal": 59096
    },
    {
      "icon_id": "7744472",
      "name": "animal-duck",
      "font_class": "animal-duck",
      "unicode": "e85d",
      "unicode_decimal": 59485
    },
    {
      "icon_id": "13896756",
      "name": "universal-credit-a",
      "font_class": "universal-credit-a",
      "unicode": "e6d9",
      "unicode_decimal": 59097
    },
    {
      "icon_id": "7693531",
      "name": "agrotechnika",
      "font_class": "agrotechnika",
      "unicode": "e743",
      "unicode_decimal": 59203
    },
    {
      "icon_id": "7744473",
      "name": "animal-deer",
      "font_class": "animal-deer",
      "unicode": "e85e",
      "unicode_decimal": 59486
    },
    {
      "icon_id": "13897006",
      "name": "weather-high-temperature",
      "font_class": "weather-high-temperature",
      "unicode": "e6da",
      "unicode_decimal": 59098
    },
    {
      "icon_id": "7693532",
      "name": "drought",
      "font_class": "drought",
      "unicode": "e744",
      "unicode_decimal": 59204
    },
    {
      "icon_id": "7744474",
      "name": "animal-goose",
      "font_class": "animal-goose",
      "unicode": "e85f",
      "unicode_decimal": 59487
    },
    {
      "icon_id": "13897007",
      "name": "weather-cloudy-a",
      "font_class": "weather-cloudy-a",
      "unicode": "e6db",
      "unicode_decimal": 59099
    },
    {
      "icon_id": "7693533",
      "name": "flood",
      "font_class": "flood",
      "unicode": "e745",
      "unicode_decimal": 59205
    },
    {
      "icon_id": "7744475",
      "name": "animal-sheep",
      "font_class": "animal-sheep",
      "unicode": "e860",
      "unicode_decimal": 59488
    },
    {
      "icon_id": "13897036",
      "name": "agriculture-crop-a",
      "font_class": "agriculture-crop-a",
      "unicode": "e6dc",
      "unicode_decimal": 59100
    },
    {
      "icon_id": "7693534",
      "name": "leaf",
      "font_class": "leaf",
      "unicode": "e746",
      "unicode_decimal": 59206
    },
    {
      "icon_id": "7744476",
      "name": "animal-pig",
      "font_class": "animal-pig",
      "unicode": "e861",
      "unicode_decimal": 59489
    },
    {
      "icon_id": "13897037",
      "name": "agriculture-grain",
      "font_class": "agriculture-grain",
      "unicode": "e6dd",
      "unicode_decimal": 59101
    },
    {
      "icon_id": "7693535",
      "name": "medicine-bottle",
      "font_class": "medicine-bottle",
      "unicode": "e747",
      "unicode_decimal": 59207
    },
    {
      "icon_id": "7765280",
      "name": "crop-corn",
      "font_class": "crop-corn",
      "unicode": "e862",
      "unicode_decimal": 59490
    },
    {
      "icon_id": "13897038",
      "name": "agriculture-farmlands-a",
      "font_class": "agriculture-farmlands-a",
      "unicode": "e6de",
      "unicode_decimal": 59102
    },
    {
      "icon_id": "7693536",
      "name": "insect",
      "font_class": "insect",
      "unicode": "e748",
      "unicode_decimal": 59208
    },
    {
      "icon_id": "7765281",
      "name": "crop-soybean",
      "font_class": "crop-soybean",
      "unicode": "e863",
      "unicode_decimal": 59491
    },
    {
      "icon_id": "14510917",
      "name": "agriculture-ecology",
      "font_class": "agriculture-ecology",
      "unicode": "e82f",
      "unicode_decimal": 59439
    },
    {
      "icon_id": "7693537",
      "name": "planter",
      "font_class": "planter",
      "unicode": "e749",
      "unicode_decimal": 59209
    },
    {
      "icon_id": "7765282",
      "name": "crop-peanut",
      "font_class": "crop-peanut",
      "unicode": "e864",
      "unicode_decimal": 59492
    },
    {
      "icon_id": "15632484",
      "name": "weather-label-icon-flood",
      "font_class": "label-icon-flood",
      "unicode": "e6df",
      "unicode_decimal": 59103
    },
    {
      "icon_id": "7693538",
      "name": "plot-management",
      "font_class": "plot-management",
      "unicode": "e74a",
      "unicode_decimal": 59210
    },
    {
      "icon_id": "7765283",
      "name": "crop-rice",
      "font_class": "crop-rice",
      "unicode": "e865",
      "unicode_decimal": 59493
    },
    {
      "icon_id": "15632803",
      "name": "weather-fill-flood",
      "font_class": "flood1",
      "unicode": "e6e0",
      "unicode_decimal": 59104
    },
    {
      "icon_id": "7693539",
      "name": "property",
      "font_class": "property",
      "unicode": "e74b",
      "unicode_decimal": 59211
    },
    {
      "icon_id": "7765284",
      "name": "fire-small",
      "font_class": "fire-small",
      "unicode": "e866",
      "unicode_decimal": 59494
    },
    {
      "icon_id": "15633004",
      "name": "weather-label-small-flood",
      "font_class": "weather-label-small-flood",
      "unicode": "e6e1",
      "unicode_decimal": 59105
    },
    {
      "icon_id": "7693540",
      "name": "tractors",
      "font_class": "tractors",
      "unicode": "e74c",
      "unicode_decimal": 59212
    },
    {
      "icon_id": "7765285",
      "name": "crop-sunflower",
      "font_class": "crop-sunflower",
      "unicode": "e867",
      "unicode_decimal": 59495
    },
    {
      "icon_id": "15633036",
      "name": "weather-flood-mappoint",
      "font_class": "weather-flood-mappoint",
      "unicode": "e6e2",
      "unicode_decimal": 59106
    },
    {
      "icon_id": "7693541",
      "name": "sensor",
      "font_class": "sensor",
      "unicode": "e74d",
      "unicode_decimal": 59213
    },
    {
      "icon_id": "7765286",
      "name": "fire-big",
      "font_class": "fire-big",
      "unicode": "e868",
      "unicode_decimal": 59496
    },
    {
      "icon_id": "17186566",
      "name": "Uni-line-order-plant",
      "font_class": "order-plant",
      "unicode": "e830",
      "unicode_decimal": 59440
    },
    {
      "icon_id": "7693542",
      "name": "shovel",
      "font_class": "shovel",
      "unicode": "e74e",
      "unicode_decimal": 59214
    },
    {
      "icon_id": "7765337",
      "name": "funnel",
      "font_class": "funnel",
      "unicode": "e869",
      "unicode_decimal": 59497
    },
    {
      "icon_id": "17186650",
      "name": "universal-safety-certificate-b",
      "font_class": "safety-certificate-b",
      "unicode": "e831",
      "unicode_decimal": 59441
    },
    {
      "icon_id": "7693548",
      "name": "bar",
      "font_class": "bar",
      "unicode": "e74f",
      "unicode_decimal": 59215
    },
    {
      "icon_id": "7872996",
      "name": "disk",
      "font_class": "disk",
      "unicode": "e86a",
      "unicode_decimal": 59498
    },
    {
      "icon_id": "17186677",
      "name": "universal-configure-b",
      "font_class": "configure-b",
      "unicode": "e832",
      "unicode_decimal": 59442
    },
    {
      "icon_id": "7693549",
      "name": "dimensionality",
      "font_class": "dimensionality",
      "unicode": "e750",
      "unicode_decimal": 59216
    },
    {
      "icon_id": "7872997",
      "name": "all",
      "font_class": "all",
      "unicode": "e86b",
      "unicode_decimal": 59499
    },
    {
      "icon_id": "17186697",
      "name": "chart-pie-d",
      "font_class": "pie-d",
      "unicode": "e833",
      "unicode_decimal": 59443
    },
    {
      "icon_id": "7693550",
      "name": "line",
      "font_class": "line",
      "unicode": "e751",
      "unicode_decimal": 59217
    },
    {
      "icon_id": "7872998",
      "name": "list-check",
      "font_class": "list-check",
      "unicode": "e86c",
      "unicode_decimal": 59500
    },
    {
      "icon_id": "17186807",
      "name": "Uni-line-publicity-magic",
      "font_class": "publicity-magic",
      "unicode": "e834",
      "unicode_decimal": 59444
    },
    {
      "icon_id": "7693551",
      "name": "dot",
      "font_class": "dot",
      "unicode": "e752",
      "unicode_decimal": 59218
    },
    {
      "icon_id": "7873033",
      "name": "agricultural-facilities",
      "font_class": "agricultural-facilities",
      "unicode": "e86d",
      "unicode_decimal": 59501
    },
    {
      "icon_id": "17206111",
      "name": "universal-align",
      "font_class": "universal-align",
      "unicode": "e6e3",
      "unicode_decimal": 59107
    },
    {
      "icon_id": "7693552",
      "name": "line-2",
      "font_class": "line-2",
      "unicode": "e753",
      "unicode_decimal": 59219
    },
    {
      "icon_id": "7873034",
      "name": "greenhouse",
      "font_class": "greenhouse",
      "unicode": "e86e",
      "unicode_decimal": 59502
    },
    {
      "icon_id": "19532134",
      "name": "universal-ticket",
      "font_class": "ticket",
      "unicode": "e606",
      "unicode_decimal": 58886
    },
    {
      "icon_id": "7693553",
      "name": "meter",
      "font_class": "meter",
      "unicode": "e754",
      "unicode_decimal": 59220
    },
    {
      "icon_id": "7873035",
      "name": "ancillary-facilities",
      "font_class": "ancillary-facilities",
      "unicode": "e86f",
      "unicode_decimal": 59503
    },
    {
      "icon_id": "22244074",
      "name": "universal-eye-close",
      "font_class": "eye-close",
      "unicode": "e835",
      "unicode_decimal": 59445
    },
    {
      "icon_id": "7693554",
      "name": "pie",
      "font_class": "pie",
      "unicode": "e755",
      "unicode_decimal": 59221
    },
    {
      "icon_id": "7873036",
      "name": "protect agriculture",
      "font_class": "protectagriculture",
      "unicode": "e870",
      "unicode_decimal": 59504
    },
    {
      "icon_id": "22310934",
      "name": "universal-water-pattern",
      "font_class": "universal-water-pattern",
      "unicode": "e62a",
      "unicode_decimal": 58922
    },
    {
      "icon_id": "7693555",
      "name": "stacking-diagram",
      "font_class": "stacking-diagram",
      "unicode": "e756",
      "unicode_decimal": 59222
    },
    {
      "icon_id": "8048963",
      "name": "contrast-2",
      "font_class": "contrast-",
      "unicode": "e871",
      "unicode_decimal": 59505
    },
    {
      "icon_id": "22310935",
      "name": "universal-legend-b",
      "font_class": "universal-legend-b",
      "unicode": "e62b",
      "unicode_decimal": 58923
    },
    {
      "icon_id": "7693556",
      "name": "radar",
      "font_class": "radar",
      "unicode": "e757",
      "unicode_decimal": 59223
    },
    {
      "icon_id": "8048964",
      "name": "location-4",
      "font_class": "location-4",
      "unicode": "e872",
      "unicode_decimal": 59506
    },
    {
      "icon_id": "7693566",
      "name": "arrows-right",
      "font_class": "arrows-right",
      "unicode": "e758",
      "unicode_decimal": 59224
    },
    {
      "icon_id": "8051514",
      "name": "contrast",
      "font_class": "contrast",
      "unicode": "e873",
      "unicode_decimal": 59507
    },
    {
      "icon_id": "7693567",
      "name": "arrows-up",
      "font_class": "arrows-up",
      "unicode": "e759",
      "unicode_decimal": 59225
    },
    {
      "icon_id": "8051515",
      "name": "contrast-3",
      "font_class": "contrast-1",
      "unicode": "e874",
      "unicode_decimal": 59508
    },
    {
      "icon_id": "7693568",
      "name": "arrows-left",
      "font_class": "arrows-left",
      "unicode": "e75a",
      "unicode_decimal": 59226
    },
    {
      "icon_id": "8159080",
      "name": "desert",
      "font_class": "desert",
      "unicode": "e875",
      "unicode_decimal": 59509
    },
    {
      "icon_id": "7693569",
      "name": "arrows-down",
      "font_class": "arrows-down",
      "unicode": "e75b",
      "unicode_decimal": 59227
    },
    {
      "icon_id": "8875151",
      "name": "granary",
      "font_class": "granary",
      "unicode": "e876",
      "unicode_decimal": 59510
    },
    {
      "icon_id": "7693570",
      "name": "double-down-single",
      "font_class": "double-down-single",
      "unicode": "e75c",
      "unicode_decimal": 59228
    },
    {
      "icon_id": "8875152",
      "name": "fertilizer",
      "font_class": "fertilizer",
      "unicode": "e877",
      "unicode_decimal": 59511
    },
    {
      "icon_id": "7693571",
      "name": "double-down-square",
      "font_class": "double-down-square",
      "unicode": "e75d",
      "unicode_decimal": 59229
    },
    {
      "icon_id": "8875153",
      "name": "granary-highyield",
      "font_class": "granary-highyield",
      "unicode": "e878",
      "unicode_decimal": 59512
    },
    {
      "icon_id": "7693572",
      "name": "double-down",
      "font_class": "double-down",
      "unicode": "e75e",
      "unicode_decimal": 59230
    },
    {
      "icon_id": "8875154",
      "name": "granary-lowyield",
      "font_class": "granary-lowyield",
      "unicode": "e879",
      "unicode_decimal": 59513
    },
    {
      "icon_id": "7693573",
      "name": "double-left-square",
      "font_class": "double-left-square",
      "unicode": "e75f",
      "unicode_decimal": 59231
    },
    {
      "icon_id": "8875155",
      "name": "pesticide",
      "font_class": "pesticide",
      "unicode": "e87a",
      "unicode_decimal": 59514
    },
    {
      "icon_id": "7693574",
      "name": "double-left",
      "font_class": "double-left",
      "unicode": "e760",
      "unicode_decimal": 59232
    },
    {
      "icon_id": "8875156",
      "name": "seed",
      "font_class": "seed",
      "unicode": "e87b",
      "unicode_decimal": 59515
    },
    {
      "icon_id": "7693575",
      "name": "double-left-single",
      "font_class": "double-left-single",
      "unicode": "e761",
      "unicode_decimal": 59233
    },
    {
      "icon_id": "8875165",
      "name": "sketch-alter",
      "font_class": "sketch-alter",
      "unicode": "e87c",
      "unicode_decimal": 59516
    },
    {
      "icon_id": "7693576",
      "name": "double-right-single",
      "font_class": "double-right-single",
      "unicode": "e762",
      "unicode_decimal": 59234
    },
    {
      "icon_id": "8875166",
      "name": "sketch-rectangular",
      "font_class": "sketch-rectangular",
      "unicode": "e87d",
      "unicode_decimal": 59517
    },
    {
      "icon_id": "7693577",
      "name": "double-right-square",
      "font_class": "double-right-square",
      "unicode": "e763",
      "unicode_decimal": 59235
    },
    {
      "icon_id": "8875167",
      "name": "sketch-circle",
      "font_class": "sketch-circle",
      "unicode": "e87e",
      "unicode_decimal": 59518
    },
    {
      "icon_id": "7693578",
      "name": "double-right",
      "font_class": "double-right",
      "unicode": "e764",
      "unicode_decimal": 59236
    },
    {
      "icon_id": "8875168",
      "name": "sketch-polygon",
      "font_class": "sketch-polygon",
      "unicode": "e87f",
      "unicode_decimal": 59519
    },
    {
      "icon_id": "7693579",
      "name": "double-up-single",
      "font_class": "double-up-single",
      "unicode": "e765",
      "unicode_decimal": 59237
    },
    {
      "icon_id": "8875178",
      "name": "list-history",
      "font_class": "list-history",
      "unicode": "e880",
      "unicode_decimal": 59520
    },
    {
      "icon_id": "7693580",
      "name": "double-up-square",
      "font_class": "double-up-square",
      "unicode": "e766",
      "unicode_decimal": 59238
    },
    {
      "icon_id": "8875179",
      "name": "flag-a",
      "font_class": "flag-a",
      "unicode": "e881",
      "unicode_decimal": 59521
    },
    {
      "icon_id": "7693581",
      "name": "double-up",
      "font_class": "double-up",
      "unicode": "e767",
      "unicode_decimal": 59239
    },
    {
      "icon_id": "8875180",
      "name": "appstore-a",
      "font_class": "appstore-a",
      "unicode": "e882",
      "unicode_decimal": 59522
    },
    {
      "icon_id": "7693582",
      "name": "single-down",
      "font_class": "down",
      "unicode": "e768",
      "unicode_decimal": 59240
    },
    {
      "icon_id": "8875202",
      "name": "soil-temperature",
      "font_class": "soil-temperature",
      "unicode": "e883",
      "unicode_decimal": 59523
    },
    {
      "icon_id": "7693583",
      "name": "exit",
      "font_class": "exit",
      "unicode": "e769",
      "unicode_decimal": 59241
    },
    {
      "icon_id": "8875203",
      "name": "soil-humidity-a",
      "font_class": "soil-humidity-a",
      "unicode": "e884",
      "unicode_decimal": 59524
    },
    {
      "icon_id": "7693584",
      "name": "fullscreen-exit",
      "font_class": "fullscreen-exit",
      "unicode": "e76a",
      "unicode_decimal": 59242
    },
    {
      "icon_id": "8875205",
      "name": "soil-temperature-a",
      "font_class": "soil-temperature-a",
      "unicode": "e886",
      "unicode_decimal": 59526
    },
    {
      "icon_id": "7693585",
      "name": "into",
      "font_class": "into",
      "unicode": "e76b",
      "unicode_decimal": 59243
    },
    {
      "icon_id": "8875206",
      "name": "transpire",
      "font_class": "transpire",
      "unicode": "e887",
      "unicode_decimal": 59527
    },
    {
      "icon_id": "7693586",
      "name": "fullscreen",
      "font_class": "fullscreen",
      "unicode": "e76c",
      "unicode_decimal": 59244
    },
    {
      "icon_id": "8875207",
      "name": "soil-humidity",
      "font_class": "soil-humidity",
      "unicode": "e888",
      "unicode_decimal": 59528
    },
    {
      "icon_id": "7693587",
      "name": "single-left",
      "font_class": "left",
      "unicode": "e76d",
      "unicode_decimal": 59245
    },
    {
      "icon_id": "8876132",
      "name": "radiation",
      "font_class": "radiation",
      "unicode": "e885",
      "unicode_decimal": 59525
    },
    {
      "icon_id": "7693588",
      "name": "menu-unfold",
      "font_class": "menu-unfold",
      "unicode": "e76e",
      "unicode_decimal": 59246
    },
    {
      "icon_id": "9098008",
      "name": "heavy-fog",
      "font_class": "heavy-fog",
      "unicode": "e601",
      "unicode_decimal": 58881
    },
    {
      "icon_id": "7693589",
      "name": "menu-fold",
      "font_class": "menu-fold",
      "unicode": "e76f",
      "unicode_decimal": 59247
    },
    {
      "icon_id": "9098009",
      "name": "cold-wave",
      "font_class": "cold-wave-a",
      "unicode": "e602",
      "unicode_decimal": 58882
    },
    {
      "icon_id": "7693590",
      "name": "point-east",
      "font_class": "point-east",
      "unicode": "e770",
      "unicode_decimal": 59248
    },
    {
      "icon_id": "9098010",
      "name": "drought",
      "font_class": "drought-a",
      "unicode": "e603",
      "unicode_decimal": 58883
    },
    {
      "icon_id": "7693591",
      "name": "point-north",
      "font_class": "point-north",
      "unicode": "e771",
      "unicode_decimal": 59249
    },
    {
      "icon_id": "9098011",
      "name": "rainstorm",
      "font_class": "rainstorm",
      "unicode": "e604",
      "unicode_decimal": 58884
    },
    {
      "icon_id": "7693592",
      "name": "point-northeast",
      "font_class": "point-northeast",
      "unicode": "e772",
      "unicode_decimal": 59250
    },
    {
      "icon_id": "9098012",
      "name": "frost",
      "font_class": "frost-a",
      "unicode": "e605",
      "unicode_decimal": 58885
    },
    {
      "icon_id": "7693593",
      "name": "point-southeast",
      "font_class": "point-southeast",
      "unicode": "e773",
      "unicode_decimal": 59251
    },
    {
      "icon_id": "9098014",
      "name": "hail",
      "font_class": "hail",
      "unicode": "e607",
      "unicode_decimal": 58887
    },
    {
      "icon_id": "7693594",
      "name": "point-south",
      "font_class": "point-south",
      "unicode": "e774",
      "unicode_decimal": 59252
    },
    {
      "icon_id": "9098016",
      "name": "Thunderstorm",
      "font_class": "Thunderstorm",
      "unicode": "e608",
      "unicode_decimal": 58888
    },
    {
      "icon_id": "7693595",
      "name": "point-northwest",
      "font_class": "point-northwest",
      "unicode": "e775",
      "unicode_decimal": 59253
    },
    {
      "icon_id": "9098017",
      "name": "gale",
      "font_class": "gale-a",
      "unicode": "e609",
      "unicode_decimal": 58889
    },
    {
      "icon_id": "7693596",
      "name": "push-down",
      "font_class": "push-down",
      "unicode": "e776",
      "unicode_decimal": 59254
    },
    {
      "icon_id": "9098018",
      "name": "haze",
      "font_class": "haze1",
      "unicode": "e60a",
      "unicode_decimal": 58890
    },
    {
      "icon_id": "7693597",
      "name": "point-southwest",
      "font_class": "point-southwest",
      "unicode": "e777",
      "unicode_decimal": 59255
    },
    {
      "icon_id": "9098019",
      "name": "sandstorm",
      "font_class": "sandstorm",
      "unicode": "e60b",
      "unicode_decimal": 58891
    },
    {
      "icon_id": "7693598",
      "name": "push-left",
      "font_class": "push-left",
      "unicode": "e778",
      "unicode_decimal": 59256
    },
    {
      "icon_id": "9098020",
      "name": "thunder",
      "font_class": "thunder",
      "unicode": "e60c",
      "unicode_decimal": 58892
    },
    {
      "icon_id": "7693599",
      "name": "push-right",
      "font_class": "push-right",
      "unicode": "e779",
      "unicode_decimal": 59257
    },
    {
      "icon_id": "9098021",
      "name": "high-temperature",
      "font_class": "high-temperature2",
      "unicode": "e60d",
      "unicode_decimal": 58893
    },
    {
      "icon_id": "7693600",
      "name": "push-up",
      "font_class": "push-up",
      "unicode": "e77a",
      "unicode_decimal": 59258
    },
    {
      "icon_id": "9098152",
      "name": "typhoon",
      "font_class": "typhoon1",
      "unicode": "e60e",
      "unicode_decimal": 58894
    },
    {
      "icon_id": "7693601",
      "name": "point-west",
      "font_class": "point-west",
      "unicode": "e77b",
      "unicode_decimal": 59259
    },
    {
      "icon_id": "9098153",
      "name": "blizzard",
      "font_class": "blizzard",
      "unicode": "e60f",
      "unicode_decimal": 58895
    },
    {
      "icon_id": "7693602",
      "name": "rollback",
      "font_class": "rollback",
      "unicode": "e77c",
      "unicode_decimal": 59260
    },
    {
      "icon_id": "9098385",
      "name": "insect-a",
      "font_class": "insect1",
      "unicode": "e610",
      "unicode_decimal": 58896
    },
    {
      "icon_id": "7693603",
      "name": "swap-left",
      "font_class": "swap-left",
      "unicode": "e77d",
      "unicode_decimal": 59261
    },
    {
      "icon_id": "9098965",
      "name": "weather-a",
      "font_class": "weather-",
      "unicode": "e611",
      "unicode_decimal": 58897
    },
    {
      "icon_id": "7693604",
      "name": "single-right",
      "font_class": "right",
      "unicode": "e77e",
      "unicode_decimal": 59262
    },
    {
      "icon_id": "9099639",
      "name": "chart-curve",
      "font_class": "Chart-",
      "unicode": "e612",
      "unicode_decimal": 58898
    },
    {
      "icon_id": "7693605",
      "name": "swap-down",
      "font_class": "swap-down",
      "unicode": "e77f",
      "unicode_decimal": 59263
    },
    {
      "icon_id": "9151375",
      "name": "road-icing",
      "font_class": "road-icing1",
      "unicode": "e613",
      "unicode_decimal": 58899
    },
    {
      "icon_id": "7693606",
      "name": "refresh",
      "font_class": "refresh",
      "unicode": "e780",
      "unicode_decimal": 59264
    },
    {
      "icon_id": "9199470",
      "name": "order-delivery",
      "font_class": "order-delivery",
      "unicode": "e614",
      "unicode_decimal": 58900
    },
    {
      "icon_id": "7693607",
      "name": "swap-right",
      "font_class": "swap-right",
      "unicode": "e781",
      "unicode_decimal": 59265
    },
    {
      "icon_id": "9199471",
      "name": "order-creation",
      "font_class": "order-creation",
      "unicode": "e615",
      "unicode_decimal": 58901
    },
    {
      "icon_id": "7693608",
      "name": "swap-up",
      "font_class": "swap-up",
      "unicode": "e782",
      "unicode_decimal": 59266
    },
    {
      "icon_id": "9199472",
      "name": "order-statistics",
      "font_class": "order-statistics",
      "unicode": "e616",
      "unicode_decimal": 58902
    },
    {
      "icon_id": "7693609",
      "name": "single-up",
      "font_class": "up",
      "unicode": "e783",
      "unicode_decimal": 59267
    },
    {
      "icon_id": "9199473",
      "name": "order",
      "font_class": "order",
      "unicode": "e617",
      "unicode_decimal": 58903
    },
    {
      "icon_id": "7693610",
      "name": "swap",
      "font_class": "swap",
      "unicode": "e784",
      "unicode_decimal": 59268
    },
    {
      "icon_id": "9199474",
      "name": "Order-submission",
      "font_class": "Order-submission",
      "unicode": "e618",
      "unicode_decimal": 58904
    },
    {
      "icon_id": "7693611",
      "name": "vertical-right",
      "font_class": "vertical-right",
      "unicode": "e785",
      "unicode_decimal": 59269
    },
    {
      "icon_id": "9199476",
      "name": "order-quality-inspection",
      "font_class": "order-quality-inspection",
      "unicode": "e61a",
      "unicode_decimal": 58906
    },
    {
      "icon_id": "7693612",
      "name": "vertical-left",
      "font_class": "vertical-left",
      "unicode": "e786",
      "unicode_decimal": 59270
    },
    {
      "icon_id": "9199494",
      "name": "order-review",
      "font_class": "order-review",
      "unicode": "e619",
      "unicode_decimal": 58905
    },
    {
      "icon_id": "7693625",
      "name": "close-circle-2",
      "font_class": "close-circle-2",
      "unicode": "e787",
      "unicode_decimal": 59271
    },
    {
      "icon_id": "9199715",
      "name": "search-a",
      "font_class": "search-a",
      "unicode": "e61b",
      "unicode_decimal": 58907
    },
    {
      "icon_id": "7693626",
      "name": "close",
      "font_class": "close",
      "unicode": "e788",
      "unicode_decimal": 59272
    },
    {
      "icon_id": "9199757",
      "name": "direction-turn-left",
      "font_class": "turn-left",
      "unicode": "e61c",
      "unicode_decimal": 58908
    },
    {
      "icon_id": "7693627",
      "name": "exclamation",
      "font_class": "exclamation",
      "unicode": "e789",
      "unicode_decimal": 59273
    },
    {
      "icon_id": "9199758",
      "name": "direction-turn-right",
      "font_class": "turn-right",
      "unicode": "e61d",
      "unicode_decimal": 58909
    },
    {
      "icon_id": "7693628",
      "name": "info-circle-2",
      "font_class": "info-circle-2",
      "unicode": "e78a",
      "unicode_decimal": 59274
    },
    {
      "icon_id": "9199961",
      "name": "tick",
      "font_class": "tick1",
      "unicode": "e61e",
      "unicode_decimal": 58910
    },
    {
      "icon_id": "7693629",
      "name": "exclamation-circle-2",
      "font_class": "exclamation-circle-2",
      "unicode": "e78b",
      "unicode_decimal": 59275
    },
    {
      "icon_id": "9199962",
      "name": "close-a",
      "font_class": "close-a",
      "unicode": "e61f",
      "unicode_decimal": 58911
    },
    {
      "icon_id": "7693630",
      "name": "info-circle",
      "font_class": "info-circle",
      "unicode": "e78c",
      "unicode_decimal": 59276
    },
    {
      "icon_id": "9200191",
      "name": "hint-success",
      "font_class": "hint-success",
      "unicode": "e620",
      "unicode_decimal": 58912
    },
    {
      "icon_id": "7693631",
      "name": "exclamation-circle",
      "font_class": "exclamation-circle",
      "unicode": "e78d",
      "unicode_decimal": 59277
    },
    {
      "icon_id": "9200192",
      "name": "hint-warning",
      "font_class": "hint-warning",
      "unicode": "e621",
      "unicode_decimal": 58913
    },
    {
      "icon_id": "7693632",
      "name": "info",
      "font_class": "info",
      "unicode": "e78e",
      "unicode_decimal": 59278
    },
    {
      "icon_id": "9200193",
      "name": "hint-prompt",
      "font_class": "hint-prompt",
      "unicode": "e622",
      "unicode_decimal": 58914
    },
    {
      "icon_id": "7693633",
      "name": "minus-circle",
      "font_class": "minus-circle",
      "unicode": "e78f",
      "unicode_decimal": 59279
    },
    {
      "icon_id": "9200194",
      "name": "hint-fail",
      "font_class": "hint-fail",
      "unicode": "e623",
      "unicode_decimal": 58915
    },
    {
      "icon_id": "7693634",
      "name": "minus",
      "font_class": "minus",
      "unicode": "e790",
      "unicode_decimal": 59280
    },
    {
      "icon_id": "9200195",
      "name": "hint-help",
      "font_class": "hint-help",
      "unicode": "e624",
      "unicode_decimal": 58916
    },
    {
      "icon_id": "7693635",
      "name": "minus-circle-2",
      "font_class": "minus-circle-2",
      "unicode": "e791",
      "unicode_decimal": 59281
    },
    {
      "icon_id": "9200329",
      "name": "checkbox-un",
      "font_class": "checkbox-un",
      "unicode": "e625",
      "unicode_decimal": 58917
    },
    {
      "icon_id": "7693636",
      "name": "pause-circle-2",
      "font_class": "pause-circle-2",
      "unicode": "e792",
      "unicode_decimal": 59282
    },
    {
      "icon_id": "9200330",
      "name": "checkbox-hecked",
      "font_class": "checkbox-hecked",
      "unicode": "e626",
      "unicode_decimal": 58918
    },
    {
      "icon_id": "7693637",
      "name": "pause",
      "font_class": "pause",
      "unicode": "e793",
      "unicode_decimal": 59283
    },
    {
      "icon_id": "9200331",
      "name": "checkbox-sel",
      "font_class": "checkbox-sel",
      "unicode": "e627",
      "unicode_decimal": 58919
    },
    {
      "icon_id": "7693638",
      "name": "pause-circle",
      "font_class": "pause-circle",
      "unicode": "e794",
      "unicode_decimal": 59284
    },
    {
      "icon_id": "9200533",
      "name": "move",
      "font_class": "move",
      "unicode": "e628",
      "unicode_decimal": 58920
    },
    {
      "icon_id": "7693639",
      "name": "play-circle-2",
      "font_class": "play-circle-2",
      "unicode": "e795",
      "unicode_decimal": 59285
    },
    {
      "icon_id": "9200534",
      "name": "full-screen",
      "font_class": "full-screen",
      "unicode": "e629",
      "unicode_decimal": 58921
    },
    {
      "icon_id": "7693640",
      "name": "play-circle",
      "font_class": "play-circle",
      "unicode": "e796",
      "unicode_decimal": 59286
    },
    {
      "icon_id": "9238859",
      "name": "order-distribution",
      "font_class": "order-distribution",
      "unicode": "e62d",
      "unicode_decimal": 58925
    },
    {
      "icon_id": "7693641",
      "name": "plus-circle",
      "font_class": "plus-circle",
      "unicode": "e797",
      "unicode_decimal": 59287
    },
    {
      "icon_id": "9241926",
      "name": "checkbox-a-un",
      "font_class": "checkbox-a-un",
      "unicode": "e62e",
      "unicode_decimal": 58926
    },
    {
      "icon_id": "7693642",
      "name": "plus",
      "font_class": "plus",
      "unicode": "e798",
      "unicode_decimal": 59288
    },
    {
      "icon_id": "9241927",
      "name": "checkbox-a-checked",
      "font_class": "checkbox-a-checked",
      "unicode": "e62f",
      "unicode_decimal": 58927
    },
    {
      "icon_id": "7693643",
      "name": "plus-circle-2",
      "font_class": "plus-circle-2",
      "unicode": "e799",
      "unicode_decimal": 59289
    },
    {
      "icon_id": "9241928",
      "name": "checkbox-a-checked-a",
      "font_class": "checkbox-a-checked-a",
      "unicode": "e630",
      "unicode_decimal": 58928
    },
    {
      "icon_id": "7693644",
      "name": "stop-circle-2",
      "font_class": "stop-circle-2",
      "unicode": "e79a",
      "unicode_decimal": 59290
    },
    {
      "icon_id": "9257834",
      "name": "universal-eye",
      "font_class": "eye-a",
      "unicode": "e631",
      "unicode_decimal": 58929
    },
    {
      "icon_id": "7693645",
      "name": "stop",
      "font_class": "stop",
      "unicode": "e79b",
      "unicode_decimal": 59291
    },
    {
      "icon_id": "9263095",
      "name": "agriculture-disaster",
      "font_class": "agriculture-disaster",
      "unicode": "e632",
      "unicode_decimal": 58930
    },
    {
      "icon_id": "7693646",
      "name": "tick-circle",
      "font_class": "tick-circle",
      "unicode": "e79c",
      "unicode_decimal": 59292
    },
    {
      "icon_id": "9263096",
      "name": "agriculture-identification",
      "font_class": "agriculture-identification",
      "unicode": "e633",
      "unicode_decimal": 58931
    },
    {
      "icon_id": "7693647",
      "name": "play",
      "font_class": "play",
      "unicode": "e79d",
      "unicode_decimal": 59293
    },
    {
      "icon_id": "9263139",
      "name": "Chart-line",
      "font_class": "Chart-line",
      "unicode": "e634",
      "unicode_decimal": 58932
    },
    {
      "icon_id": "7693648",
      "name": "tick-circle-2",
      "font_class": "tick-circle-2",
      "unicode": "e79e",
      "unicode_decimal": 59294
    },
    {
      "icon_id": "9263252",
      "name": "universal-position",
      "font_class": "position",
      "unicode": "e635",
      "unicode_decimal": 58933
    },
    {
      "icon_id": "7693649",
      "name": "tick-vulgar",
      "font_class": "tick-vulgar",
      "unicode": "e79f",
      "unicode_decimal": 59295
    },
    {
      "icon_id": "9282348",
      "name": "icon-mappoint-yield",
      "font_class": "icon-mappoint-yield",
      "unicode": "e636",
      "unicode_decimal": 58934
    },
    {
      "icon_id": "7693650",
      "name": "tick",
      "font_class": "tick",
      "unicode": "e7a0",
      "unicode_decimal": 59296
    },
    {
      "icon_id": "9282411",
      "name": "icon-mappoint-expfield",
      "font_class": "icon-mappoint-shiyantianweizhizuobiao",
      "unicode": "e637",
      "unicode_decimal": 58935
    },
    {
      "icon_id": "7693651",
      "name": "stop-circle",
      "font_class": "stop-circle",
      "unicode": "e7a1",
      "unicode_decimal": 59297
    },
    {
      "icon_id": "9304302",
      "name": "universal-user",
      "font_class": "user1",
      "unicode": "e638",
      "unicode_decimal": 58936
    },
    {
      "icon_id": "7693652",
      "name": "warning-2",
      "font_class": "warning-2",
      "unicode": "e7a2",
      "unicode_decimal": 59298
    },
    {
      "icon_id": "9304303",
      "name": "universal-closed",
      "font_class": "closed",
      "unicode": "e639",
      "unicode_decimal": 58937
    },
    {
      "icon_id": "7693653",
      "name": "warning",
      "font_class": "warning",
      "unicode": "e7a3",
      "unicode_decimal": 59299
    },
    {
      "icon_id": "9304306",
      "name": "universal-password",
      "font_class": "password",
      "unicode": "e63a",
      "unicode_decimal": 58938
    },
    {
      "icon_id": "7693666",
      "name": "coverage",
      "font_class": "coverage",
      "unicode": "e7a4",
      "unicode_decimal": 59300
    },
    {
      "icon_id": "9319398",
      "name": "universal-process",
      "font_class": "universal-process",
      "unicode": "e63b",
      "unicode_decimal": 58939
    },
    {
      "icon_id": "7693667",
      "name": "compass",
      "font_class": "compass",
      "unicode": "e7a5",
      "unicode_decimal": 59301
    },
    {
      "icon_id": "9319399",
      "name": "universal-client",
      "font_class": "universal-client",
      "unicode": "e63c",
      "unicode_decimal": 58940
    },
    {
      "icon_id": "7693668",
      "name": "layer",
      "font_class": "layer",
      "unicode": "e7a6",
      "unicode_decimal": 59302
    },
    {
      "icon_id": "9319400",
      "name": "universal-users",
      "font_class": "universal-users",
      "unicode": "e63d",
      "unicode_decimal": 58941
    },
    {
      "icon_id": "7693669",
      "name": "legend-2",
      "font_class": "legend-2",
      "unicode": "e7a7",
      "unicode_decimal": 59303
    },
    {
      "icon_id": "9319401",
      "name": "universal-contract",
      "font_class": "universal-contract",
      "unicode": "e63e",
      "unicode_decimal": 58942
    },
    {
      "icon_id": "7693670",
      "name": "legend",
      "font_class": "legend",
      "unicode": "e7a8",
      "unicode_decimal": 59304
    },
    {
      "icon_id": "9319402",
      "name": "universal-role",
      "font_class": "universal-role",
      "unicode": "e63f",
      "unicode_decimal": 58943
    },
    {
      "icon_id": "7693671",
      "name": "legend-3",
      "font_class": "legend-3",
      "unicode": "e7a9",
      "unicode_decimal": 59305
    },
    {
      "icon_id": "9648273",
      "name": "weather-rainstorm",
      "font_class": "rainstorm1",
      "unicode": "e642",
      "unicode_decimal": 58946
    },
    {
      "icon_id": "7693672",
      "name": "location-end",
      "font_class": "location-end",
      "unicode": "e7aa",
      "unicode_decimal": 59306
    },
    {
      "icon_id": "9648274",
      "name": "weather-cold-wave",
      "font_class": "cold-wave2",
      "unicode": "e643",
      "unicode_decimal": 58947
    },
    {
      "icon_id": "7693673",
      "name": "orientation",
      "font_class": "orientation",
      "unicode": "e7ab",
      "unicode_decimal": 59307
    },
    {
      "icon_id": "9648276",
      "name": "weather-high-temperature",
      "font_class": "high-temperature3",
      "unicode": "e645",
      "unicode_decimal": 58949
    },
    {
      "icon_id": "7693674",
      "name": "N",
      "font_class": "N",
      "unicode": "e7ac",
      "unicode_decimal": 59308
    },
    {
      "icon_id": "9649923",
      "name": "weather-drought",
      "font_class": "weather-drought-a",
      "unicode": "e644",
      "unicode_decimal": 58948
    },
    {
      "icon_id": "7693677",
      "name": "location-start",
      "font_class": "location-start",
      "unicode": "e7af",
      "unicode_decimal": 59311
    },
    {
      "icon_id": "9995583",
      "name": "universal-order-report",
      "font_class": "universal-order-report",
      "unicode": "e646",
      "unicode_decimal": 58950
    },
    {
      "icon_id": "7693678",
      "name": "parcel-survey",
      "font_class": "parcel-survey",
      "unicode": "e7b0",
      "unicode_decimal": 59312
    },
    {
      "icon_id": "9995670",
      "name": "universal-transform",
      "font_class": "universal-transform",
      "unicode": "e647",
      "unicode_decimal": 58951
    },
    {
      "icon_id": "7693679",
      "name": "path",
      "font_class": "path",
      "unicode": "e7b1",
      "unicode_decimal": 59313
    },
    {
      "icon_id": "9995681",
      "name": "universal-import",
      "font_class": "universal-import",
      "unicode": "e648",
      "unicode_decimal": 58952
    },
    {
      "icon_id": "7693680",
      "name": "plot",
      "font_class": "plot",
      "unicode": "e7b2",
      "unicode_decimal": 59314
    },
    {
      "icon_id": "10019838",
      "name": "map-position",
      "font_class": "map-position",
      "unicode": "e649",
      "unicode_decimal": 58953
    },
    {
      "icon_id": "7693681",
      "name": "polt-2",
      "font_class": "polt-2",
      "unicode": "e7b3",
      "unicode_decimal": 59315
    },
    {
      "icon_id": "10147177",
      "name": "universal-index",
      "font_class": "universal-index",
      "unicode": "e64a",
      "unicode_decimal": 58954
    },
    {
      "icon_id": "7693682",
      "name": "plots",
      "font_class": "plots",
      "unicode": "e7b4",
      "unicode_decimal": 59316
    },
    {
      "icon_id": "10147178",
      "name": "universal-user-b",
      "font_class": "universal-user-b",
      "unicode": "e64b",
      "unicode_decimal": 58955
    },
    {
      "icon_id": "7693683",
      "name": "S",
      "font_class": "S",
      "unicode": "e7b5",
      "unicode_decimal": 59317
    },
    {
      "icon_id": "10147179",
      "name": "universal-message-a",
      "font_class": "universal-message-a",
      "unicode": "e64c",
      "unicode_decimal": 58956
    },
    {
      "icon_id": "7693684",
      "name": "software-management",
      "font_class": "software-management",
      "unicode": "e7b6",
      "unicode_decimal": 59318
    },
    {
      "icon_id": "10147441",
      "name": "universal-service",
      "font_class": "universal-service",
      "unicode": "e64d",
      "unicode_decimal": 58957
    },
    {
      "icon_id": "7693685",
      "name": "terrain",
      "font_class": "terrain",
      "unicode": "e7b7",
      "unicode_decimal": 59319
    },
    {
      "icon_id": "10147442",
      "name": "universal-privacy-a",
      "font_class": "universal-privacy-a",
      "unicode": "e64e",
      "unicode_decimal": 58958
    },
    {
      "icon_id": "7693697",
      "name": "bell",
      "font_class": "bell",
      "unicode": "e7b8",
      "unicode_decimal": 59320
    },
    {
      "icon_id": "10147805",
      "name": "singlebox-b",
      "font_class": "singlebox-b",
      "unicode": "e64f",
      "unicode_decimal": 58959
    },
    {
      "icon_id": "7693698",
      "name": "appstore",
      "font_class": "appstore",
      "unicode": "e7b9",
      "unicode_decimal": 59321
    },
    {
      "icon_id": "10147806",
      "name": "singlebox-a",
      "font_class": "singlebox-a",
      "unicode": "e650",
      "unicode_decimal": 58960
    },
    {
      "icon_id": "7693699",
      "name": "audit",
      "font_class": "audit",
      "unicode": "e7ba",
      "unicode_decimal": 59322
    },
    {
      "icon_id": "10147807",
      "name": "singlebox-c",
      "font_class": "singlebox-c",
      "unicode": "e651",
      "unicode_decimal": 58961
    },
    {
      "icon_id": "7693700",
      "name": "besom",
      "font_class": "besom",
      "unicode": "e7bb",
      "unicode_decimal": 59323
    },
    {
      "icon_id": "10148400",
      "name": "agriculture-area",
      "font_class": "agriculture-area",
      "unicode": "e652",
      "unicode_decimal": 58962
    },
    {
      "icon_id": "7693701",
      "name": "bulb",
      "font_class": "bulb",
      "unicode": "e7bc",
      "unicode_decimal": 59324
    },
    {
      "icon_id": "10394553",
      "name": "weather-wind",
      "font_class": "weather-wind",
      "unicode": "e653",
      "unicode_decimal": 58963
    },
    {
      "icon_id": "7693702",
      "name": "camera",
      "font_class": "camera",
      "unicode": "e7bd",
      "unicode_decimal": 59325
    },
    {
      "icon_id": "10394721",
      "name": "temperature-a",
      "font_class": "temperature-a",
      "unicode": "e82e",
      "unicode_decimal": 59438
    },
    {
      "icon_id": "7693703",
      "name": "calendar",
      "font_class": "calendar",
      "unicode": "e7be",
      "unicode_decimal": 59326
    },
    {
      "icon_id": "10446788",
      "name": "flat-down",
      "font_class": "flat-down",
      "unicode": "e654",
      "unicode_decimal": 58964
    },
    {
      "icon_id": "7693704",
      "name": "close-circle",
      "font_class": "close-circle",
      "unicode": "e7bf",
      "unicode_decimal": 59327
    },
    {
      "icon_id": "10446789",
      "name": "flat-left",
      "font_class": "flat-left",
      "unicode": "e655",
      "unicode_decimal": 58965
    },
    {
      "icon_id": "7693705",
      "name": "coin",
      "font_class": "coin",
      "unicode": "e7c0",
      "unicode_decimal": 59328
    },
    {
      "icon_id": "10446790",
      "name": "flat-right",
      "font_class": "flat-right",
      "unicode": "e656",
      "unicode_decimal": 58966
    },
    {
      "icon_id": "7693706",
      "name": "copy",
      "font_class": "copy",
      "unicode": "e7c1",
      "unicode_decimal": 59329
    },
    {
      "icon_id": "10446791",
      "name": "flat-up",
      "font_class": "flat-up",
      "unicode": "e657",
      "unicode_decimal": 58967
    },
    {
      "icon_id": "7693707",
      "name": "configure",
      "font_class": "configure",
      "unicode": "e7c2",
      "unicode_decimal": 59330
    },
    {
      "icon_id": "10571806",
      "name": "forest-fire-insurance",
      "font_class": "forest-fire-insurance",
      "unicode": "e668",
      "unicode_decimal": 58984
    },
    {
      "icon_id": "7693708",
      "name": "cpu",
      "font_class": "cpu",
      "unicode": "e7c3",
      "unicode_decimal": 59331
    },
    {
      "icon_id": "10573848",
      "name": "label-icon-drought",
      "font_class": "label-icon-drought",
      "unicode": "e669",
      "unicode_decimal": 58985
    },
    {
      "icon_id": "7693709",
      "name": "desktop-chart",
      "font_class": "desktop-chart",
      "unicode": "e7c4",
      "unicode_decimal": 59332
    },
    {
      "icon_id": "10573849",
      "name": "label-icon-gale",
      "font_class": "label-icon-gale",
      "unicode": "e66a",
      "unicode_decimal": 58986
    },
    {
      "icon_id": "7693710",
      "name": "desktop-configure",
      "font_class": "desktop-configure",
      "unicode": "e7c5",
      "unicode_decimal": 59333
    },
    {
      "icon_id": "10573850",
      "name": "label-icon-hail",
      "font_class": "label-icon-hail",
      "unicode": "e66b",
      "unicode_decimal": 58987
    },
    {
      "icon_id": "7693711",
      "name": "download-2",
      "font_class": "download-2",
      "unicode": "e7c6",
      "unicode_decimal": 59334
    },
    {
      "icon_id": "10573851",
      "name": "label-icon-blizzard",
      "font_class": "label-icon-blizzard",
      "unicode": "e66c",
      "unicode_decimal": 58988
    },
    {
      "icon_id": "7693712",
      "name": "download",
      "font_class": "download",
      "unicode": "e7c7",
      "unicode_decimal": 59335
    },
    {
      "icon_id": "10573852",
      "name": "label-icon-frost",
      "font_class": "label-icon-frost",
      "unicode": "e66d",
      "unicode_decimal": 58989
    },
    {
      "icon_id": "7693713",
      "name": "delete",
      "font_class": "delete",
      "unicode": "e7c8",
      "unicode_decimal": 59336
    },
    {
      "icon_id": "10573853",
      "name": "label-icon-haze",
      "font_class": "label-icon-haze",
      "unicode": "e66e",
      "unicode_decimal": 58990
    },
    {
      "icon_id": "7693714",
      "name": "desktop",
      "font_class": "desktop",
      "unicode": "e7c9",
      "unicode_decimal": 59337
    },
    {
      "icon_id": "10573854",
      "name": "label-icon-thunderstorm",
      "font_class": "label-icon-thunderstorm",
      "unicode": "e66f",
      "unicode_decimal": 58991
    },
    {
      "icon_id": "7693715",
      "name": "elipsis",
      "font_class": "elipsis",
      "unicode": "e7ca",
      "unicode_decimal": 59338
    },
    {
      "icon_id": "10573855",
      "name": "label-icon-high-temperature",
      "font_class": "label-icon-high-temperature",
      "unicode": "e670",
      "unicode_decimal": 58992
    },
    {
      "icon_id": "7693716",
      "name": "edit",
      "font_class": "edit",
      "unicode": "e7cb",
      "unicode_decimal": 59339
    },
    {
      "icon_id": "10573856",
      "name": "label-icon-road-icing",
      "font_class": "label-icon-road-icing",
      "unicode": "e671",
      "unicode_decimal": 58993
    },
    {
      "icon_id": "7693717",
      "name": "eye",
      "font_class": "eye",
      "unicode": "e7cc",
      "unicode_decimal": 59340
    },
    {
      "icon_id": "10573857",
      "name": "label-icon-cold-wave",
      "font_class": "label-icon-cold-wave",
      "unicode": "e672",
      "unicode_decimal": 58994
    },
    {
      "icon_id": "7693718",
      "name": "file-add",
      "font_class": "file-add",
      "unicode": "e7cd",
      "unicode_decimal": 59341
    },
    {
      "icon_id": "10573858",
      "name": "label-icon-thunder",
      "font_class": "label-icon-thunder",
      "unicode": "e673",
      "unicode_decimal": 58995
    },
    {
      "icon_id": "7693719",
      "name": "farm",
      "font_class": "farm",
      "unicode": "e7ce",
      "unicode_decimal": 59342
    },
    {
      "icon_id": "10573859",
      "name": "label-icon-typhoon",
      "font_class": "label-icon-typhoon",
      "unicode": "e674",
      "unicode_decimal": 58996
    },
    {
      "icon_id": "7693720",
      "name": "file-bar-chart",
      "font_class": "file-bar-chart",
      "unicode": "e7cf",
      "unicode_decimal": 59343
    },
    {
      "icon_id": "10573860",
      "name": "label-icon-forest-fire-insurance",
      "font_class": "label-icon-forest-fire-insurance",
      "unicode": "e675",
      "unicode_decimal": 58997
    },
    {
      "icon_id": "7693721",
      "name": "files-search",
      "font_class": "files-search",
      "unicode": "e7d0",
      "unicode_decimal": 59344
    },
    {
      "icon_id": "10573861",
      "name": "label-icon-rainstorm",
      "font_class": "label-icon-rainstorm",
      "unicode": "e676",
      "unicode_decimal": 58998
    },
    {
      "icon_id": "7693722",
      "name": "file",
      "font_class": "file",
      "unicode": "e7d1",
      "unicode_decimal": 59345
    },
    {
      "icon_id": "10573862",
      "name": "label-icon-heavy-fog",
      "font_class": "label-icon-heavy-fog",
      "unicode": "e677",
      "unicode_decimal": 58999
    },
    {
      "icon_id": "7693723",
      "name": "flag",
      "font_class": "flag",
      "unicode": "e7d2",
      "unicode_decimal": 59346
    },
    {
      "icon_id": "10573863",
      "name": "label-icon-sandstorm",
      "font_class": "label-icon-sandstorm",
      "unicode": "e678",
      "unicode_decimal": 59000
    },
    {
      "icon_id": "7693724",
      "name": "files-text",
      "font_class": "files-text",
      "unicode": "e7d3",
      "unicode_decimal": 59347
    },
    {
      "icon_id": "10660151",
      "name": "label-icon-thunder-gust",
      "font_class": "label-icon-thunder-gust",
      "unicode": "e67a",
      "unicode_decimal": 59002
    },
    {
      "icon_id": "7693725",
      "name": "folder-open",
      "font_class": "folder-open",
      "unicode": "e7d4",
      "unicode_decimal": 59348
    },
    {
      "icon_id": "10668331",
      "name": "cold-mappoint",
      "font_class": "cold-mappoint",
      "unicode": "e67b",
      "unicode_decimal": 59003
    },
    {
      "icon_id": "7693726",
      "name": "folder",
      "font_class": "folder",
      "unicode": "e7d5",
      "unicode_decimal": 59349
    },
    {
      "icon_id": "10668759",
      "name": "thunder-gust-mappoint",
      "font_class": "thunder-gust-mappoint-a",
      "unicode": "e67f",
      "unicode_decimal": 59007
    },
    {
      "icon_id": "7693727",
      "name": "folder-add",
      "font_class": "folder-add",
      "unicode": "e7d6",
      "unicode_decimal": 59350
    },
    {
      "icon_id": "10742928",
      "name": "label-icon-landslide",
      "font_class": "label-icon-landslide",
      "unicode": "e680",
      "unicode_decimal": 59008
    },
    {
      "icon_id": "7693728",
      "name": "gago",
      "font_class": "gago",
      "unicode": "e7d7",
      "unicode_decimal": 59351
    },
    {
      "icon_id": "10742948",
      "name": "thunderstorm-mappoint",
      "font_class": "thunderstorm-mappoint",
      "unicode": "e681",
      "unicode_decimal": 59009
    },
    {
      "icon_id": "7693729",
      "name": "home",
      "font_class": "home",
      "unicode": "e7d8",
      "unicode_decimal": 59352
    },
    {
      "icon_id": "10742949",
      "name": "landslide-mappoint",
      "font_class": "landslide-mappoint",
      "unicode": "e682",
      "unicode_decimal": 59010
    },
    {
      "icon_id": "7693730",
      "name": "heart",
      "font_class": "heart",
      "unicode": "e7d9",
      "unicode_decimal": 59353
    },
    {
      "icon_id": "10743000",
      "name": "thunder-gust",
      "font_class": "thunder-gust-b",
      "unicode": "e685",
      "unicode_decimal": 59013
    },
    {
      "icon_id": "7693731",
      "name": "label",
      "font_class": "label",
      "unicode": "e7da",
      "unicode_decimal": 59354
    },
    {
      "icon_id": "10743001",
      "name": "thunderstorm",
      "font_class": "thunderstorm-a",
      "unicode": "e686",
      "unicode_decimal": 59014
    },
    {
      "icon_id": "7693732",
      "name": "lock",
      "font_class": "lock",
      "unicode": "e7db",
      "unicode_decimal": 59355
    },
    {
      "icon_id": "10743002",
      "name": "wild-fire",
      "font_class": "wild-fire",
      "unicode": "e687",
      "unicode_decimal": 59015
    },
    {
      "icon_id": "7693733",
      "name": "link",
      "font_class": "link",
      "unicode": "e7dc",
      "unicode_decimal": 59356
    },
    {
      "icon_id": "10743003",
      "name": "landslide",
      "font_class": "landslide",
      "unicode": "e688",
      "unicode_decimal": 59016
    },
    {
      "icon_id": "7693734",
      "name": "magnifier",
      "font_class": "magnifier",
      "unicode": "e7dd",
      "unicode_decimal": 59357
    },
    {
      "icon_id": "10743004",
      "name": "thunderstorm-gales",
      "font_class": "thunderstorm-gales",
      "unicode": "e689",
      "unicode_decimal": 59017
    },
    {
      "icon_id": "7693735",
      "name": "loading-3-quarters",
      "font_class": "loading-3-quarters",
      "unicode": "e7de",
      "unicode_decimal": 59358
    },
    {
      "icon_id": "10743109",
      "name": "label-icon-thunder-gust",
      "font_class": "label-icon-thunder-gust-a",
      "unicode": "e68a",
      "unicode_decimal": 59018
    },
    {
      "icon_id": "7693736",
      "name": "message",
      "font_class": "message",
      "unicode": "e7df",
      "unicode_decimal": 59359
    },
    {
      "icon_id": "10758458",
      "name": "direction-arrow-fill",
      "font_class": "direction-arrow-fill",
      "unicode": "e68c",
      "unicode_decimal": 59020
    },
    {
      "icon_id": "7693737",
      "name": "picture",
      "font_class": "picture",
      "unicode": "e7e0",
      "unicode_decimal": 59360
    },
    {
      "icon_id": "10800975",
      "name": "weather-label-small-coldwave",
      "font_class": "weather-label-small-coldwave",
      "unicode": "e658",
      "unicode_decimal": 58968
    },
    {
      "icon_id": "7693738",
      "name": "placeholder",
      "font_class": "placeholder",
      "unicode": "e7e1",
      "unicode_decimal": 59361
    },
    {
      "icon_id": "10800976",
      "name": "weather-label-small-drought",
      "font_class": "weather-label-small-drought",
      "unicode": "e659",
      "unicode_decimal": 58969
    },
    {
      "icon_id": "7693739",
      "name": "poweroff",
      "font_class": "poweroff",
      "unicode": "e7e2",
      "unicode_decimal": 59362
    },
    {
      "icon_id": "10800977",
      "name": "weather-label-small-lightning",
      "font_class": "weather-label-small-lightning",
      "unicode": "e65a",
      "unicode_decimal": 58970
    },
    {
      "icon_id": "7693740",
      "name": "probe",
      "font_class": "probe",
      "unicode": "e7e3",
      "unicode_decimal": 59363
    },
    {
      "icon_id": "10800978",
      "name": "weather-label-small-frost",
      "font_class": "weather-label-small-frost",
      "unicode": "e65b",
      "unicode_decimal": 58971
    },
    {
      "icon_id": "7693741",
      "name": "projection",
      "font_class": "projection",
      "unicode": "e7e4",
      "unicode_decimal": 59364
    },
    {
      "icon_id": "10800979",
      "name": "weather-label-small-gale",
      "font_class": "weather-label-small-gale",
      "unicode": "e65c",
      "unicode_decimal": 58972
    },
    {
      "icon_id": "7693742",
      "name": "relation",
      "font_class": "relation",
      "unicode": "e7e5",
      "unicode_decimal": 59365
    },
    {
      "icon_id": "10800980",
      "name": "weather-label-small-heatwave",
      "font_class": "weather-label-small-heatwave",
      "unicode": "e65d",
      "unicode_decimal": 58973
    },
    {
      "icon_id": "7693743",
      "name": "qrcode",
      "font_class": "qrcode",
      "unicode": "e7e6",
      "unicode_decimal": 59366
    },
    {
      "icon_id": "10800981",
      "name": "weather-label-small-sandstorm",
      "font_class": "weather-label-small-sandstorm",
      "unicode": "e65e",
      "unicode_decimal": 58974
    },
    {
      "icon_id": "7693744",
      "name": "rmb",
      "font_class": "rmb",
      "unicode": "e7e7",
      "unicode_decimal": 59367
    },
    {
      "icon_id": "10800982",
      "name": "weather-label-small-blizzard",
      "font_class": "weather-label-small-blizzard",
      "unicode": "e65f",
      "unicode_decimal": 58975
    },
    {
      "icon_id": "7693745",
      "name": "report",
      "font_class": "report",
      "unicode": "e7e8",
      "unicode_decimal": 59368
    },
    {
      "icon_id": "10800983",
      "name": "weather-label-small-cold",
      "font_class": "weather-label-small-cold",
      "unicode": "e660",
      "unicode_decimal": 58976
    },
    {
      "icon_id": "7693746",
      "name": "report-text",
      "font_class": "report-text",
      "unicode": "e7e9",
      "unicode_decimal": 59369
    },
    {
      "icon_id": "10800984",
      "name": "weather-label-small-hail",
      "font_class": "weather-label-small-hail",
      "unicode": "e661",
      "unicode_decimal": 58977
    },
    {
      "icon_id": "7693747",
      "name": "safety-certificate",
      "font_class": "safety-certificate",
      "unicode": "e7ea",
      "unicode_decimal": 59370
    },
    {
      "icon_id": "10800985",
      "name": "weather-label-small-haze",
      "font_class": "weather-label-small-haze",
      "unicode": "e662",
      "unicode_decimal": 58978
    },
    {
      "icon_id": "7693748",
      "name": "scan",
      "font_class": "scan",
      "unicode": "e7eb",
      "unicode_decimal": 59371
    },
    {
      "icon_id": "10800986",
      "name": "weather-label-small-thunder-gust",
      "font_class": "weather-label-small-thunder-gust",
      "unicode": "e663",
      "unicode_decimal": 58979
    },
    {
      "icon_id": "7693749",
      "name": "setting",
      "font_class": "setting",
      "unicode": "e7ec",
      "unicode_decimal": 59372
    },
    {
      "icon_id": "10800987",
      "name": "weather-label-small-thunderstorm",
      "font_class": "weather-label-small-thunderstorm",
      "unicode": "e664",
      "unicode_decimal": 58980
    },
    {
      "icon_id": "7693750",
      "name": "setting-3",
      "font_class": "setting-3",
      "unicode": "e7ed",
      "unicode_decimal": 59373
    },
    {
      "icon_id": "10800988",
      "name": "weather-label-small-landslide",
      "font_class": "weather-label-small-landslide",
      "unicode": "e665",
      "unicode_decimal": 58981
    },
    {
      "icon_id": "7693751",
      "name": "table",
      "font_class": "table",
      "unicode": "e7ee",
      "unicode_decimal": 59374
    },
    {
      "icon_id": "10800989",
      "name": "weather-label-small-typhoon",
      "font_class": "weather-label-small-typhoon",
      "unicode": "e666",
      "unicode_decimal": 58982
    },
    {
      "icon_id": "7693752",
      "name": "star",
      "font_class": "star",
      "unicode": "e7ef",
      "unicode_decimal": 59375
    },
    {
      "icon_id": "10800990",
      "name": "weather-label-small-rainstorm",
      "font_class": "weather-label-small-rainstorm",
      "unicode": "e667",
      "unicode_decimal": 58983
    },
    {
      "icon_id": "7693753",
      "name": "tool",
      "font_class": "tool",
      "unicode": "e7f0",
      "unicode_decimal": 59376
    },
    {
      "icon_id": "10800991",
      "name": "weather-label-small-wildfire",
      "font_class": "weather-label-small-wildfire",
      "unicode": "e679",
      "unicode_decimal": 59001
    },
    {
      "icon_id": "7693754",
      "name": "user-list",
      "font_class": "user-list",
      "unicode": "e7f1",
      "unicode_decimal": 59377
    },
    {
      "icon_id": "10800992",
      "name": "weather-label-small-heavyfog",
      "font_class": "weather-label-small-heavyfog",
      "unicode": "e67c",
      "unicode_decimal": 59004
    },
    {
      "icon_id": "7693755",
      "name": "setting-2",
      "font_class": "setting-2",
      "unicode": "e7f2",
      "unicode_decimal": 59378
    },
    {
      "icon_id": "10800993",
      "name": "weather-label-small-roadicing",
      "font_class": "weather-label-small-roadicing",
      "unicode": "e67d",
      "unicode_decimal": 59005
    },
    {
      "icon_id": "7693756",
      "name": "uploading",
      "font_class": "uploading",
      "unicode": "e7f3",
      "unicode_decimal": 59379
    },
    {
      "icon_id": "10800994",
      "name": "weather-label-small-thunderstormgales",
      "font_class": "weather-label-small-thunderstormgales",
      "unicode": "e67e",
      "unicode_decimal": 59006
    },
    {
      "icon_id": "7693757",
      "name": "user",
      "font_class": "user",
      "unicode": "e7f4",
      "unicode_decimal": 59380
    },
    {
      "icon_id": "10949633",
      "name": "chart-form",
      "font_class": "chart-form",
      "unicode": "e683",
      "unicode_decimal": 59011
    },
    {
      "icon_id": "7693758",
      "name": "vidio",
      "font_class": "vidio",
      "unicode": "e7f5",
      "unicode_decimal": 59381
    },
    {
      "icon_id": "10949634",
      "name": "chart-barchart",
      "font_class": "chart-barchart",
      "unicode": "e684",
      "unicode_decimal": 59012
    },
    {
      "icon_id": "7693759",
      "name": "users",
      "font_class": "users",
      "unicode": "e7f6",
      "unicode_decimal": 59382
    },
    {
      "icon_id": "11062482",
      "name": "universal-card",
      "font_class": "universal-card",
      "unicode": "e68b",
      "unicode_decimal": 59019
    }
  ]
}
